fastf1/__init__.py
fastf1/_api.py
fastf1/_version.py
fastf1/api.py
fastf1/core.py
fastf1/events.py
fastf1/legacy.py
fastf1/logger.py
fastf1/req.py
fastf1/utils.py
fastf1/ergast/__init__.py
fastf1/ergast/interface.py
fastf1/ergast/legacy.py
fastf1/ergast/sphinx.py
fastf1/ergast/structure.py
fastf1/internals/__init__.py
fastf1/internals/fuzzy.py
fastf1/internals/pandas_base.py
fastf1/internals/pandas_extensions.py
fastf1/livetiming/__init__.py
fastf1/livetiming/__main__.py
fastf1/livetiming/client.py
fastf1/livetiming/data.py
fastf1/mvapi/__init__.py
fastf1/mvapi/api.py
fastf1/mvapi/data.py
fastf1/mvapi/internals.py
fastf1/plotting/__init__.py
fastf1/plotting/_backend.py
fastf1/plotting/_base.py
fastf1/plotting/_interface.py
fastf1/plotting/_plotting.py
fastf1/plotting/_constants/__init__.py
fastf1/plotting/_constants/base.py
fastf1/plotting/_constants/season2018.py
fastf1/plotting/_constants/season2019.py
fastf1/plotting/_constants/season2020.py
fastf1/plotting/_constants/season2021.py
fastf1/plotting/_constants/season2022.py
fastf1/plotting/_constants/season2023.py
fastf1/plotting/_constants/season2024.py
fastf1/plotting/_constants/season2025.py
fastf1/signalr_aio/LICENSE
fastf1/signalr_aio/README.md
fastf1/signalr_aio/__init__.py
fastf1/signalr_aio/_connection.py
fastf1/signalr_aio/events/__init__.py
fastf1/signalr_aio/events/_events.py
fastf1/signalr_aio/hubs/__init__.py
fastf1/signalr_aio/hubs/_hub.py
fastf1/signalr_aio/transports/__init__.py
fastf1/signalr_aio/transports/_exceptions.py
fastf1/signalr_aio/transports/_parameters.py
fastf1/signalr_aio/transports/_queue_events.py
fastf1/signalr_aio/transports/_transport.py
fastf1-3.5.2.dist-info/METADATA
fastf1-3.5.2.dist-info/WHEEL
fastf1-3.5.2.dist-info/licenses/LICENSE
fastf1-3.5.2.dist-info/RECORD
