Metadata-Version: 2.4
Name: fastf1
Version: 3.5.2
Summary: Python package for accessing and analyzing Formula 1 results, schedules, timing data and telemetry.
Project-URL: Source Code, https://github.com/theOehrly/Fast-F1
Project-URL: Documentation, https://docs.fastf1.dev
Author: Philipp Schaefer
Author-email: oehrly@mailbox.org
License: MIT License
License-File: LICENSE
Requires-Python: >=3.9
Requires-Dist: matplotlib<4.0.0,>=3.5.1
Requires-Dist: numpy<3.0.0,>=1.23.1
Requires-Dist: pandas<3.0.0,>=1.4.1
Requires-Dist: python-dateutil
Requires-Dist: rapidfuzz
Requires-Dist: requests-cache>=1.0.0
Requires-Dist: requests>=2.28.1
Requires-Dist: scipy<2.0.0,>=1.8.1
Requires-Dist: timple>=0.1.6
Requires-Dist: websockets<14,>=10.3
